[
  {
    "ContainingType": "Api.Controllers.BusController",
    "Method": "GetAsync",
    "RelativePath": "api/Bus",
    "HttpMethod": "GET",
    "IsController": true,
    "Order": 0,
    "Parameters": [],
    "ReturnTypes": [
      {
        "Type": "System.Object",
        "MediaTypes": [
          "text/plain",
          "application/json",
          "text/json"
        ],
        "StatusCode": 200
      }
    ]
  },
  {
    "ContainingType": "Api.Controllers.BusController",
    "Method": "PostAsync",
    "RelativePath": "api/Bus",
    "HttpMethod": "POST",
    "IsController": true,
    "Order": 0,
    "Parameters": [
      {
        "Name": "setValue",
        "Type": "System.String",
        "IsRequired": false
      }
    ],
    "ReturnTypes": []
  }
]